{"notes":[{"lane":1.0,"songPosition":969,"isHold":false,"holdLength":0},{"lane":0.0,"songPosition":1469,"isHold":false,"holdLength":0},{"lane":1.0,"songPosition":1969,"isHold":false,"holdLength":0},{"lane":0.0,"songPosition":2469,"isHold":false,"holdLength":0},{"lane":1.0,"songPosition":2969,"isHold":false,"holdLength":0},{"lane":0.0,"songPosition":3469,"isHold":false,"holdLength":0},{"lane":1.0,"songPosition":3969,"isHold":false,"holdLength":0},{"lane":0.0,"songPosition":4469,"isHold":false,"holdLength":0},{"lane":1.0,"songPosition":4969,"isHold":false,"holdLength":0},{"lane":0.0,"songPosition":5469,"isHold":false,"holdLength":0},{"lane":1.0,"songPosition":5969,"isHold":false,"holdLength":0},{"lane":0.0,"songPosition":6469,"isHold":false,"holdLength":0},{"lane":1.0,"songPosition":6969,"isHold":false,"holdLength":0},{"lane":0.0,"songPosition":7469,"isHold":false,"holdLength":0},{"lane":1.0,"songPosition":7969,"isHold":false,"holdLength":0},{"lane":0.0,"songPosition":8469,"isHold":false,"holdLength":0},{"lane":1.0,"songPosition":8969,"isHold":false,"holdLength":0},{"lane":0.0,"songPosition":9469,"isHold":false,"holdLength":0},{"lane":1.0,"songPosition":9969,"isHold":false,"holdLength":0},{"lane":0.0,"songPosition":10469,"isHold":false,"holdLength":0},{"lane":1.0,"songPosition":10969,"isHold":false,"holdLength":0},{"lane":0.0,"songPosition":11469,"isHold":false,"holdLength":0},{"lane":1.0,"songPosition":11969,"isHold":false,"holdLength":0},{"lane":0.0,"songPosition":12469,"isHold":false,"holdLength":0},{"lane":1.0,"songPosition":12969,"isHold":false,"holdLength":0},{"lane":0.0,"songPosition":13469,"isHold":false,"holdLength":0},{"lane":1.0,"songPosition":13969,"isHold":false,"holdLength":0},{"lane":0.0,"songPosition":14469,"isHold":false,"holdLength":0},{"lane":1.0,"songPosition":14969,"isHold":false,"holdLength":0},{"lane":0.0,"songPosition":15469,"isHold":false,"holdLength":0},{"lane":1.0,"songPosition":15969,"isHold":false,"holdLength":0},{"lane":0.0,"songPosition":16469,"isHold":false,"holdLength":0},{"lane":1.0,"songPosition":16969,"isHold":false,"holdLength":0},{"lane":0.0,"songPosition":17469,"isHold":false,"holdLength":0},{"lane":1.0,"songPosition":17969,"isHold":false,"holdLength":0},{"lane":0.0,"songPosition":18469,"isHold":false,"holdLength":0},{"lane":1.0,"songPosition":18969,"isHold":false,"holdLength":0},{"lane":0.0,"songPosition":19469,"isHold":false,"holdLength":0},{"lane":1.0,"songPosition":19969,"isHold":false,"holdLength":0},{"lane":0.0,"songPosition":20469,"isHold":false,"holdLength":0},{"lane":1.0,"songPosition":20969,"isHold":false,"holdLength":0}]}