{"notes":[{"lane":0,"songPosition":500,"isHold":false,"holdLength":0},{"lane":1,"songPosition":1000,"isHold":false,"holdLength":0},{"lane":0,"songPosition":1500,"isHold":false,"holdLength":0},{"lane":1,"songPosition":2000,"isHold":false,"holdLength":0},{"lane":0,"songPosition":2500,"isHold":false,"holdLength":0},{"lane":3,"songPosition":3000,"isHold":false,"holdLength":0},{"lane":2,"songPosition":3500,"isHold":false,"holdLength":0},{"lane":5,"songPosition":4000,"isHold":false,"holdLength":0},{"lane":0,"songPosition":5000,"isHold":false,"holdLength":0},{"lane":1,"songPosition":6000,"isHold":false,"holdLength":0},{"lane":0,"songPosition":6500,"isHold":false,"holdLength":0},{"lane":1,"songPosition":7000,"isHold":false,"holdLength":0},{"lane":0,"songPosition":8000,"isHold":false,"holdLength":0},{"lane":0,"songPosition":9000,"isHold":false,"holdLength":0},{"lane":5,"songPosition":10000,"isHold":false,"holdLength":0},{"lane":4,"songPosition":10500,"isHold":false,"holdLength":0},{"lane":3,"songPosition":11000,"isHold":false,"holdLength":0},{"lane":0,"songPosition":12000,"isHold":false,"holdLength":0},{"lane":1,"songPosition":12500,"isHold":false,"holdLength":0},{"lane":0,"songPosition":13000,"isHold":false,"holdLength":0},{"lane":3,"songPosition":14000,"isHold":false,"holdLength":0},{"lane":4,"songPosition":14500,"isHold":false,"holdLength":0},{"lane":3,"songPosition":15000,"isHold":false,"holdLength":0},{"lane":2,"songPosition":16000,"isHold":false,"holdLength":0},{"lane":4,"songPosition":16500,"isHold":false,"holdLength":0},{"lane":3,"songPosition":17000,"isHold":false,"holdLength":0},{"lane":0,"songPosition":18000,"isHold":false,"holdLength":0},{"lane":1,"songPosition":19000,"isHold":false,"holdLength":0},{"lane":3,"songPosition":20000,"isHold":false,"holdLength":0},{"lane":2,"songPosition":20500,"isHold":false,"holdLength":0},{"lane":4,"songPosition":21000,"isHold":false,"holdLength":0},{"lane":0,"songPosition":22000,"isHold":false,"holdLength":0},{"lane":1,"songPosition":23000,"isHold":false,"holdLength":0},{"lane":5,"songPosition":24000,"isHold":false,"holdLength":0},{"lane":4,"songPosition":24500,"isHold":false,"holdLength":0},{"lane":3,"songPosition":25000,"isHold":false,"holdLength":0},{"lane":2,"songPosition":25500,"isHold":false,"holdLength":0},{"lane":3,"songPosition":26000,"isHold":false,"holdLength":0},{"lane":5,"songPosition":26500,"isHold":false,"holdLength":0},{"lane":4,"songPosition":27000,"isHold":false,"holdLength":0},{"lane":0,"songPosition":28000,"isHold":false,"holdLength":0},{"lane":1,"songPosition":28500,"isHold":false,"holdLength":0},{"lane":0,"songPosition":29000,"isHold":false,"holdLength":0},{"lane":0,"songPosition":30000,"isHold":false,"holdLength":0},{"lane":2,"songPosition":31000,"isHold":false,"holdLength":0},{"lane":3,"songPosition":32000,"isHold":false,"holdLength":0},{"lane":5,"songPosition":32500,"isHold":false,"holdLength":0},{"lane":4,"songPosition":33000,"isHold":false,"holdLength":0},{"lane":3,"songPosition":33500,"isHold":false,"holdLength":0},{"lane":2,"songPosition":34000,"isHold":false,"holdLength":0},{"lane":4,"songPosition":34500,"isHold":false,"holdLength":0},{"lane":5,"songPosition":35000,"isHold":false,"holdLength":0},{"lane":1,"songPosition":36000,"isHold":false,"holdLength":0},{"lane":2,"songPosition":37000,"isHold":false,"holdLength":0},{"lane":3,"songPosition":38000,"isHold":false,"holdLength":0},{"lane":2,"songPosition":38500,"isHold":false,"holdLength":0},{"lane":5,"songPosition":39000,"isHold":false,"holdLength":0},{"lane":2,"songPosition":40000,"isHold":false,"holdLength":0},{"lane":3,"songPosition":40500,"isHold":false,"holdLength":0},{"lane":2,"songPosition":41000,"isHold":false,"holdLength":0},{"lane":4,"songPosition":41500,"isHold":false,"holdLength":0},{"lane":2,"songPosition":42000,"isHold":false,"holdLength":0},{"lane":3,"songPosition":42500,"isHold":false,"holdLength":0},{"lane":5,"songPosition":43000,"isHold":false,"holdLength":0},{"lane":0,"songPosition":44000,"isHold":false,"holdLength":0},{"lane":1,"songPosition":45000,"isHold":false,"holdLength":0},{"lane":3,"songPosition":46000,"isHold":false,"holdLength":0},{"lane":2,"songPosition":46500,"isHold":false,"holdLength":0},{"lane":1,"songPosition":47000,"isHold":false,"holdLength":0},{"lane":5,"songPosition":48000,"isHold":false,"holdLength":0},{"lane":4,"songPosition":48500,"isHold":false,"holdLength":0},{"lane":5,"songPosition":49000,"isHold":false,"holdLength":0},{"lane":2,"songPosition":49500,"isHold":false,"holdLength":0},{"lane":2,"songPosition":50000,"isHold":false,"holdLength":0},{"lane":3,"songPosition":50500,"isHold":false,"holdLength":0},{"lane":4,"songPosition":51000,"isHold":false,"holdLength":0},{"lane":1,"songPosition":52000,"isHold":false,"holdLength":0},{"lane":0,"songPosition":53000,"isHold":false,"holdLength":0},{"lane":1,"songPosition":54000,"isHold":false,"holdLength":0},{"lane":5,"songPosition":55000,"isHold":false,"holdLength":0},{"lane":0,"songPosition":56000,"isHold":false,"holdLength":0}]}